Metadata-Version: 2.4
Name: bigwig_loader
Version: 0.3.1
Summary: Machine Learning Data Loader for Collections of BigWig Files
Author-email: Joren Retel <joren.retel@pfizer.com>
License: Apache-2.0
Project-URL: homepage, https://github.com/pfizer-opensource/bigwig-loader
Keywords: epigenetics,bigwig,fasta
Classifier: Development Status :: 3 - Alpha
Classifier: Intended Audience :: Science/Research
Classifier: Programming Language :: Python
Classifier: Programming Language :: Python :: 3 :: Only
Classifier: Programming Language :: Python :: 3.10
Classifier: Programming Language :: Python :: 3.11
Classifier: Programming Language :: Python :: 3.12
Classifier: Topic :: Scientific/Engineering
Classifier: Topic :: Utilities
Requires-Python: >=3.10
License-File: LICENSE
Requires-Dist: numpy
Requires-Dist: cupy
Requires-Dist: cython
Requires-Dist: pandas
Requires-Dist: ncls
Requires-Dist: pyfaidx
Requires-Dist: pydantic
Requires-Dist: pydantic-settings
Requires-Dist: python-dotenv
Requires-Dist: universal_pathlib
Requires-Dist: natsort
Provides-Extra: test
Requires-Dist: mypy; extra == "test"
Requires-Dist: pytest; extra == "test"
Requires-Dist: pyBigWig; extra == "test"
Provides-Extra: dev
Requires-Dist: bigwig_loader[test]; extra == "dev"
Requires-Dist: black; extra == "dev"
Requires-Dist: isort; extra == "dev"
Requires-Dist: bandit; extra == "dev"
Requires-Dist: pip-tools; extra == "dev"
Requires-Dist: pre-commit; extra == "dev"
Dynamic: license-file
